{
  "type": "PullRequest",
  "pulls": [
    {
      "type": "pull",
      "order": 1,
      "from": "Afghanistan",
      "to": "Albania",
      "startLat": "33.93911",
      "startLng": "67.709953",
      "endLat": "41.153332",
      "endLng": "20.168331",
      "arcAlt": 0.05
    },
    {
      "type": "pull",
      "order": 1,
      "from": "Albania",
      "to": "Algeria",
      "startLat": "41.153332",
      "startLng": "20.168331",
      "endLat": "28.033886",
      "endLng": "1.659626",
      "arcAlt": 0.05
    },
    {
      "type": "pull",
      "order": 1,
      "from": "Algeria",
      "to": "Andorra",
      "startLat": "28.033886",
      "startLng": "1.659626",
      "endLat": "42.506285",
      "endLng": "1.521801",
      "arcAlt": 0.05
    },
    {
      "type": "pull",
      "order": 1,
      "from": "Andorra",
      "to": "Angola",
      "startLat": "42.506285",
      "startLng": "1.521801",
      "endLat": "-11.202692",
      "endLng": "17.873887",
      "arcAlt": 0.05
    },
    {
      "type": "pull",
      "order": 1,
      "from": "Antigua and Barbuda",
      "to": "Argentina",
      "startLat": "17.060816",
      "startLng": "-61.796428",
      "endLat": "-38.416097",
      "endLng": "-63.616672",
      "arcAlt": 0.05
    },
    {
      "type": "pull",
      "order": 2,
      "from": "Argentina",
      "to": "Armenia",
      "startLat": "-38.416097",
      "startLng": "-63.616672",
      "endLat": "40.069099",
      "endLng": "45.038189",
      "arcAlt": 0.05
    },
    {
      "type": "pull",
      "order": 2,
      "from": "Armenia",
      "to": "Australia",
      "startLat": "40.069099",
      "startLng": "45.038189",
      "endLat": "-25.274398",
      "endLng": "133.775136",
      "arcAlt": 0.05
    },
    {
      "type": "pull",
      "order": 2,
      "from": "Australia",
      "to": "Austria",
      "startLat": "-25.274398",
      "startLng": "133.775136",
      "endLat": "47.516231",
      "endLng": "14.550072",
      "arcAlt": 0.05
    },
    {
      "type": "pull",
      "order": 2,
      "from": "Austria",
      "to": "Azerbaijan",
      "startLat": "47.516231",
      "startLng": "14.550072",
      "endLat": "40.143105",
      "endLng": "47.576927",
      "arcAlt": 0.05
    },
    {
      "type": "pull",
      "order": 2,
      "from": "Azerbaijan",
      "to": "Bahamas",
      "startLat": "40.143105",
      "startLng": "47.576927",
      "endLat": "25.03428",
      "endLng": "-77.39628",
      "arcAlt": 0.05
    },
    {
      "type": "pull",
      "order": 3,
      "from": "Bahamas",
      "to": "Bahrain",
      "startLat": "25.03428",
      "startLng": "-77.39628",
      "endLat": "25.930414",
      "endLng": "50.637772",
      "arcAlt": 0.05
    },
    {
      "type": "pull",
      "order": 3,
      "from": "Bahrain",
      "to": "Bangladesh",
      "startLat": "25.930414",
      "startLng": "50.637772",
      "endLat": "23.684994",
      "endLng": "90.356331",
      "arcAlt": 0.05
    },
    {
      "type": "pull",
      "order": 3,
      "from": "Bangladesh",
      "to": "Barbados",
      "startLat": "23.684994",
      "startLng": "90.356331",
      "endLat": "13.193887",
      "endLng": "-59.543198",
      "arcAlt": 0.05
    },
    {
      "type": "pull",
      "order": 3,
      "from": "Barbados",
      "to": "Belarus",
      "startLat": "13.193887",
      "startLng": "-59.543198",
      "endLat": "53.709807",
      "endLng": "27.953389",
      "arcAlt": 0.05
    },
    {
      "type": "pull",
      "order": 3,
      "from": "Belarus",
      "to": "Belgium",
      "startLat": "53.709807",
      "startLng": "27.953389",
      "endLat": "50.503887",
      "endLng": "4.469936",
      "arcAlt": 0.05
    },
    {
      "type": "pull",
      "order": 4,
      "from": "Belgium",
      "to": "Belize",
      "startLat": "50.503887",
      "startLng": "4.469936",
      "endLat": "17.189877",
      "endLng": "-88.49765",
      "arcAlt": 0.05
    },
    {
      "type": "pull",
      "order": 4,
      "from": "Belize",
      "to": "Benin",
      "startLat": "17.189877",
      "startLng": "-88.49765",
      "endLat": "9.30769",
      "endLng": "2.315834",
      "arcAlt": 0.05
    },
    {
      "type": "pull",
      "order": 4,
      "from": "Benin",
      "to": "Bhutan",
      "startLat": "9.30769",
      "startLng": "2.315834",
      "endLat": "27.514162",
      "endLng": "90.433601",
      "arcAlt": 0.05
    },
    {
      "type": "pull",
      "order": 4,
      "from": "Bolivia",
      "to": "Bosnia and Herzegovina",
      "startLat": "-16.290154",
      "startLng": "-63.588653",
      "endLat": "43.915886",
      "endLng": "17.679076",
      "arcAlt": 0.05
    },
    {
      "type": "pull",
      "order": 4,
      "from": "Bosnia and Herzegovina",
      "to": "Botswana",
      "startLat": "43.915886",
      "startLng": "17.679076",
      "endLat": "-22.328474",
      "endLng": "24.684866",
      "arcAlt": 0.05
    },
    {
      "type": "pull",
      "order": 5,
      "from": "Botswana",
      "to": "Brazil",
      "startLat": "-22.328474",
      "startLng": "24.684866",
      "endLat": "-14.235004",
      "endLng": "-51.92528",
      "arcAlt": 0.05
    },
    {
      "type": "pull",
      "order": 5,
      "from": "Brazil",
      "to": "Brunei",
      "startLat": "-14.235004",
      "startLng": "-51.92528",
      "endLat": "4.535277",
      "endLng": "114.727669",
      "arcAlt": 0.05
    },
    {
      "type": "pull",
      "order": 5,
      "from": "Brunei",
      "to": "Bulgaria",
      "startLat": "4.535277",
      "startLng": "114.727669",
      "endLat": "42.733883",
      "endLng": "25.48583",
      "arcAlt": 0.05
    },
    {
      "type": "pull",
      "order": 5,
      "from": "Bulgaria",
      "to": "Burkina Faso",
      "startLat": "42.733883",
      "startLng": "25.48583",
      "endLat": "12.238333",
      "endLng": "-1.561593",
      "arcAlt": 0.05
    },
    {
      "type": "pull",
      "order": 5,
      "from": "Burkina Faso",
      "to": "Burundi",
      "startLat": "12.238333",
      "startLng": "-1.561593",
      "endLat": "-3.373056",
      "endLng": "29.918886",
      "arcAlt": 0.05
    },
    {
      "type": "pull",
      "order": 6,
      "from": "Burundi",
      "to": "Cabo Verde",
      "startLat": "-3.373056",
      "startLng": "29.918886",
      "endLat": "16.5388",
      "endLng": "-23.0418",
      "arcAlt": 0.05
    },
    {
      "type": "pull",
      "order": 6,
      "from": "Cabo Verde",
      "to": "Cambodia",
      "startLat": "16.5388",
      "startLng": "-23.0418",
      "endLat": "12.565679",
      "endLng": "104.990963",
      "arcAlt": 0.05
    },
    {
      "type": "pull",
      "order": 6,
      "from": "Cambodia",
      "to": "Cameroon",
      "startLat": "12.565679",
      "startLng": "104.990963",
      "endLat": "7.369722",
      "endLng": "12.354722",
      "arcAlt": 0.05
    },
    {
      "type": "pull",
      "order": 6,
      "from": "Cameroon",
      "to": "Canada",
      "startLat": "7.369722",
      "startLng": "12.354722",
      "endLat": "56.130366",
      "endLng": "-106.346771",
      "arcAlt": 0.05
    },
    {
      "type": "pull",
      "order": 6,
      "from": "Canada",
      "to": "Central African Republic",
      "startLat": "56.130366",
      "startLng": "-106.346771",
      "endLat": "6.611111",
      "endLng": "20.939444",
      "arcAlt": 0.05
    },
    {
      "type": "pull",
      "order": 7,
      "from": "Central African Republic",
      "to": "Chad",
      "startLat": "6.611111",
      "startLng": "20.939444",
      "endLat": "15.454166",
      "endLng": "18.732207",
      "arcAlt": 0.05
    },
    {
      "type": "pull",
      "order": 7,
      "from": "Chad",
      "to": "Chile",
      "startLat": "15.454166",
      "startLng": "18.732207",
      "endLat": "-35.675147",
      "endLng": "-71.542969",
      "arcAlt": 0.05
    },
    {
      "type": "pull",
      "order": 7,
      "from": "Chile",
      "to": "China",
      "startLat": "-35.675147",
      "startLng": "-71.542969",
      "endLat": "35.86166",
      "endLng": "104.195397",
      "arcAlt": 0.05
    },
    {
      "type": "pull",
      "order": 7,
      "from": "Colombia",
      "to": "Comoros",
      "startLat": "4.570868",
      "startLng": "-74.297333",
      "endLat": "-11.875001",
      "endLng": "43.872219",
      "arcAlt": 0.05
    },
    {
      "type": "pull",
      "order": 7,
      "from": "Comoros",
      "to": "Congo, Democratic Republic of the",
      "startLat": "-11.875001",
      "startLng": "43.872219",
      "endLat": "-4.038333",
      "endLng": "21.758664",
      "arcAlt": 0.05
    },
    {
      "type": "pull",
      "order": 8,
      "from": "Congo, Democratic Republic of the",
      "to": "Congo, Republic of the",
      "startLat": "-4.038333",
      "startLng": "21.758664",
      "endLat": "-0.228021",
      "endLng": "15.827659",
      "arcAlt": 0.05
    },
    {
      "type": "pull",
      "order": 8,
      "from": "Congo, Republic of the",
      "to": "Costa Rica",
      "startLat": "-0.228021",
      "startLng": "15.827659",
      "endLat": "9.748917",
      "endLng": "-83.753428",
      "arcAlt": 0.05
    },
    {
      "type": "pull",
      "order": 8,
      "from": "Costa Rica",
      "to": "Cote d'Ivoire",
      "startLat": "9.748917",
      "startLng": "-83.753428",
      "endLat": "7.539989",
      "endLng": "-5.54708",
      "arcAlt": 0.05
    },
    {
      "type": "pull",
      "order": 8,
      "from": "Cote d'Ivoire",
      "to": "Croatia",
      "startLat": "7.539989",
      "startLng": "-5.54708",
      "endLat": "45.1",
      "endLng": "15.2",
      "arcAlt": 0.05
    },
    {
      "type": "pull",
      "order": 8,
      "from": "Croatia",
      "to": "Cuba",
      "startLat": "45.1",
      "startLng": "15.2",
      "endLat": "21.521757",
      "endLng": "-77.781167",
      "arcAlt": 0.05
    },
    {
      "type": "pull",
      "order": 9,
      "from": "Cuba",
      "to": "Cyprus",
      "startLat": "21.521757",
      "startLng": "-77.781167",
      "endLat": "35.126413",
      "endLng": "33.429859",
      "arcAlt": 0.05
    },
    {
      "type": "pull",
      "order": 9,
      "from": "Cyprus",
      "to": "Czech Republic",
      "startLat": "35.126413",
      "startLng": "33.429859",
      "endLat": "49.817492",
      "endLng": "15.472962",
      "arcAlt": 0.05
    },
    {
      "type": "pull",
      "order": 9,
      "from": "Czech Republic",
      "to": "Denmark",
      "startLat": "49.817492",
      "startLng": "15.472962",
      "endLat": "56.26392",
      "endLng": "9.501785",
      "arcAlt": 0.05
    },
    {
      "type": "pull",
      "order": 9,
      "from": "Denmark",
      "to": "Djibouti",
      "startLat": "56.26392",
      "startLng": "9.501785",
      "endLat": "11.825138",
      "endLng": "42.590275",
      "arcAlt": 0.05
    },
    {
      "type": "pull",
      "order": 9,
      "from": "Djibouti",
      "to": "Dominica",
      "startLat": "11.825138",
      "startLng": "42.590275",
      "endLat": "15.414999",
      "endLng": "-61.370976",
      "arcAlt": 0.05
    },
    {
      "type": "pull",
      "order": 10,
      "from": "Dominica",
      "to": "Dominican Republic",
      "startLat": "15.414999",
      "startLng": "-61.370976",
      "endLat": "18.735693",
      "endLng": "-70.162651",
      "arcAlt": 0.05
    },
    {
      "type": "pull",
      "order": 10,
      "from": "Dominican Republic",
      "to": "East Timor (Timor-Leste)",
      "startLat": "18.735693",
      "startLng": "-70.162651",
      "endLat": "-8.874217",
      "endLng": "125.727539",
      "arcAlt": 0.05
    },
    {
      "type": "pull",
      "order": 10,
      "from": "East Timor (Timor-Leste)",
      "to": "Ecuador",
      "startLat": "-8.874217",
      "startLng": "125.727539",
      "endLat": "-1.831239",
      "endLng": "-78.183406",
      "arcAlt": 0.05
    },
    {
      "type": "pull",
      "order": 10,
      "from": "Ecuador",
      "to": "Egypt",
      "startLat": "-1.831239",
      "startLng": "-78.183406",
      "endLat": "26.820553",
      "endLng": "30.802498",
      "arcAlt": 0.05
    },
    {
      "type": "pull",
      "order": 10,
      "from": "Egypt",
      "to": "El Salvador",
      "startLat": "26.820553",
      "startLng": "30.802498",
      "endLat": "13.794185",
      "endLng": "-88.89653",
      "arcAlt": 0.05
    },
    {
      "type": "pull",
      "order": 11,
      "from": "El Salvador",
      "to": "Equatorial Guinea",
      "startLat": "13.794185",
      "startLng": "-88.89653",
      "endLat": "1.650801",
      "endLng": "10.267895",
      "arcAlt": 0.05
    },
    {
      "type": "pull",
      "order": 11,
      "from": "Equatorial Guinea",
      "to": "Eritrea",
      "startLat": "1.650801",
      "startLng": "10.267895",
      "endLat": "15.179384",
      "endLng": "39.782334",
      "arcAlt": 0.05
    },
    {
      "type": "pull",
      "order": 11,
      "from": "Eritrea",
      "to": "Estonia",
      "startLat": "15.179384",
      "startLng": "39.782334",
      "endLat": "9.145",
      "endLng": "25.4296",
      "arcAlt": 0.05
    },
    {
      "type": "pull",
      "order": 11,
      "from": "Estonia",
      "to": "Eswatini",
      "startLat": "9.145",
      "startLng": "25.4296",
      "endLat": "-26.522503",
      "endLng": "31.465866",
      "arcAlt": 0.05
    },
    {
      "type": "pull",
      "order": 11,
      "from": "Eswatini",
      "to": "Ethiopia",
      "startLat": "-26.522503",
      "startLng": "31.465866",
      "endLat": "9.145",
      "endLng": "40.489673",
      "arcAlt": 0.05
    },
    {
      "type": "pull",
      "order": 12,
      "from": "Ethiopia",
      "to": "Fiji",
      "startLat": "9.145",
      "startLng": "40.489673",
      "endLat": "-17.713371",
      "endLng": "178.065032",
      "arcAlt": 0.05
    },
    {
      "type": "pull",
      "order": 12,
      "from": "Fiji",
      "to": "Finland",
      "startLat": "-17.713371",
      "startLng": "178.065032",
      "endLat": "61.92411",
      "endLng": "25.748151",
      "arcAlt": 0.05
    },
    {
      "type": "pull",
      "order": 12,
      "from": "France",
      "to": "Gabon",
      "startLat": "46.603354",
      "startLng": "1.888334",
      "endLat": "-0.803689",
      "endLng": "11.609444",
      "arcAlt": 0.05
    },
    {
      "type": "pull",
      "order": 12,
      "from": "Gabon",
      "to": "Gambia",
      "startLat": "-0.803689",
      "startLng": "11.609444",
      "endLat": "13.443182",
      "endLng": "-15.310139",
      "arcAlt": 0.05
    },
    {
      "type": "pull",
      "order": 12,
      "from": "Gambia",
      "to": "Georgia",
      "startLat": "13.443182",
      "startLng": "-15.310139",
      "endLat": "32.1656221",
      "endLng": "34.8476719",
      "arcAlt": 0.05
    },
    {
      "type": "pull",
      "order": 13,
      "from": "Georgia",
      "to": "Germany",
      "startLat": "32.1656221",
      "startLng": "34.8476719",
      "endLat": "51.165691",
      "endLng": "10.451526",
      "arcAlt": 0.05
    },
    {
      "type": "pull",
      "order": 13,
      "from": "Germany",
      "to": "Ghana",
      "startLat": "51.165691",
      "startLng": "10.451526",
      "endLat": "7.946527",
      "endLng": "-1.023194",
      "arcAlt": 0.05
    },
    {
      "type": "pull",
      "order": 13,
      "from": "Ghana",
      "to": "Greece",
      "startLat": "7.946527",
      "startLng": "-1.023194",
      "endLat": "39.074208",
      "endLng": "21.824312",
      "arcAlt": 0.05
    },
    {
      "type": "pull",
      "order": 13,
      "from": "Greece",
      "to": "Grenada",
      "startLat": "39.074208",
      "startLng": "21.824312",
      "endLat": "12.262776",
      "endLng": "-61.604171",
      "arcAlt": 0.05
    },
    {
      "type": "pull",
      "order": 13,
      "from": "Grenada",
      "to": "Guatemala",
      "startLat": "12.262776",
      "startLng": "-61.604171",
      "endLat": "15.783471",
      "endLng": "-90.230759",
      "arcAlt": 0.05
    },
    {
      "type": "pull",
      "order": 14,
      "from": "Guatemala",
      "to": "Guinea",
      "startLat": "15.783471",
      "startLng": "-90.230759",
      "endLat": "9.945587",
      "endLng": "-9.696645",
      "arcAlt": 0.05
    },
    {
      "type": "pull",
      "order": 14,
      "from": "Guinea",
      "to": "Guinea-Bissau",
      "startLat": "9.945587",
      "startLng": "-9.696645",
      "endLat": "11.803749",
      "endLng": "-15.180413",
      "arcAlt": 0.05
    },
    {
      "type": "pull",
      "order": 14,
      "from": "Guinea-Bissau",
      "to": "Guyana",
      "startLat": "11.803749",
      "startLng": "-15.180413",
      "endLat": "4.860416",
      "endLng": "-58.93018",
      "arcAlt": 0.05
    },
    {
      "type": "pull",
      "order": 14,
      "from": "Guyana",
      "to": "Haiti",
      "startLat": "4.860416",
      "startLng": "-58.93018",
      "endLat": "18.971187",
      "endLng": "-72.285215",
      "arcAlt": 0.05
    },
    {
      "type": "pull",
      "order": 14,
      "from": "Honduras",
      "to": "Hungary",
      "startLat": "15.199999",
      "startLng": "-86.241905",
      "endLat": "47.162494",
      "endLng": "19.503304",
      "arcAlt": 0.05
    },
    {
      "type": "pull",
      "order": 15,
      "from": "Hungary",
      "to": "Iceland",
      "startLat": "47.162494",
      "startLng": "19.503304",
      "endLat": "64.963051",
      "endLng": "-19.020835",
      "arcAlt": 0.05
    },
    {
      "type": "pull",
      "order": 15,
      "from": "Iceland",
      "to": "India",
      "startLat": "64.963051",
      "startLng": "-19.020835",
      "endLat": "20.593684",
      "endLng": "78.96288",
      "arcAlt": 0.05
    },
    {
      "type": "pull",
      "order": 15,
      "from": "India",
      "to": "Indonesia",
      "startLat": "20.593684",
      "startLng": "78.96288",
      "endLat": "-0.789275",
      "endLng": "113.921327",
      "arcAlt": 0.05
    },
    {
      "type": "pull",
      "order": 15,
      "from": "Indonesia",
      "to": "Iran",
      "startLat": "-0.789275",
      "startLng": "113.921327",
      "endLat": "32.427908",
      "endLng": "53.688046",
      "arcAlt": 0.05
    },
    {
      "type": "pull",
      "order": 15,
      "from": "Iran",
      "to": "Iraq",
      "startLat": "32.427908",
      "startLng": "53.688046",
      "endLat": "33.223191",
      "endLng": "43.679291",
      "arcAlt": 0.05
    },
    {
      "type": "pull",
      "order": 16,
      "from": "Iraq",
      "to": "Ireland",
      "startLat": "33.223191",
      "startLng": "43.679291",
      "endLat": "53.41291",
      "endLng": "-8.24389",
      "arcAlt": 0.05
    },
    {
      "type": "pull",
      "order": 16,
      "from": "Ireland",
      "to": "Israel",
      "startLat": "53.41291",
      "startLng": "-8.24389",
      "endLat": "31.046051",
      "endLng": "34.851612",
      "arcAlt": 0.05
    },
    {
      "type": "pull",
      "order": 16,
      "from": "Israel",
      "to": "Italy",
      "startLat": "31.046051",
      "startLng": "34.851612",
      "endLat": "41.87194",
      "endLng": "12.56738",
      "arcAlt": 0.05
    },
    {
      "type": "pull",
      "order": 16,
      "from": "Italy",
      "to": "Jamaica",
      "startLat": "41.87194",
      "startLng": "12.56738",
      "endLat": "18.109581",
      "endLng": "-77.297508",
      "arcAlt": 0.05
    },
    {
      "type": "pull",
      "order": 16,
      "from": "Jamaica",
      "to": "Japan",
      "startLat": "18.109581",
      "startLng": "-77.297508",
      "endLat": "36.204824",
      "endLng": "138.252924",
      "arcAlt": 0.05
    },
    {
      "type": "pull",
      "order": 17,
      "from": "Japan",
      "to": "Jordan",
      "startLat": "36.204824",
      "startLng": "138.252924",
      "endLat": "30.585164",
      "endLng": "36.238414",
      "arcAlt": 0.05
    },
    {
      "type": "pull",
      "order": 17,
      "from": "Jordan",
      "to": "Kazakhstan",
      "startLat": "30.585164",
      "startLng": "36.238414",
      "endLat": "48.019573",
      "endLng": "66.923684",
      "arcAlt": 0.05
    },
    {
      "type": "pull",
      "order": 17,
      "from": "Kenya",
      "to": "Kiribati",
      "startLat": "-0.0236",
      "startLng": "37.9062",
      "endLat": "1.8709",
      "endLng": "-157.3627",
      "arcAlt": 0.05
    },
    {
      "type": "pull",
      "order": 17,
      "from": "Kiribati",
      "to": "Korea, North",
      "startLat": "1.8709",
      "startLng": "-157.3627",
      "endLat": "40.3399",
      "endLng": "127.5101",
      "arcAlt": 0.05
    },
    {
      "type": "pull",
      "order": 17,
      "from": "Korea, North",
      "to": "Korea, South",
      "startLat": "40.3399",
      "startLng": "127.5101",
      "endLat": "35.9078",
      "endLng": "127.7669",
      "arcAlt": 0.05
    },
    {
      "type": "pull",
      "order": 18,
      "from": "Korea, South",
      "to": "Kosovo",
      "startLat": "35.9078",
      "startLng": "127.7669",
      "endLat": "42.6026",
      "endLng": "20.903",
      "arcAlt": 0.05
    },
    {
      "type": "pull",
      "order": 18,
      "from": "Kosovo",
      "to": "Kuwait",
      "startLat": "42.6026",
      "startLng": "20.903",
      "endLat": "29.3759",
      "endLng": "47.9774",
      "arcAlt": 0.05
    },
    {
      "type": "pull",
      "order": 18,
      "from": "Kuwait",
      "to": "Kyrgyzstan",
      "startLat": "29.3759",
      "startLng": "47.9774",
      "endLat": "41.2044",
      "endLng": "74.7661",
      "arcAlt": 0.05
    },
    {
      "type": "pull",
      "order": 18,
      "from": "Kyrgyzstan",
      "to": "Laos",
      "startLat": "41.2044",
      "startLng": "74.7661",
      "endLat": "19.8563",
      "endLng": "102.4955",
      "arcAlt": 0.05
    },
    {
      "type": "pull",
      "order": 18,
      "from": "Laos",
      "to": "Latvia",
      "startLat": "19.8563",
      "startLng": "102.4955",
      "endLat": "56.8796",
      "endLng": "24.6032",
      "arcAlt": 0.05
    },
    {
      "type": "pull",
      "order": 19,
      "from": "Latvia",
      "to": "Lebanon",
      "startLat": "56.8796",
      "startLng": "24.6032",
      "endLat": "33.8547",
      "endLng": "35.8623",
      "arcAlt": 0.05
    },
    {
      "type": "pull",
      "order": 19,
      "from": "Lebanon",
      "to": "Lesotho",
      "startLat": "33.8547",
      "startLng": "35.8623",
      "endLat": "-29.609988",
      "endLng": "28.233608",
      "arcAlt": 0.05
    },
    {
      "type": "pull",
      "order": 19,
      "from": "Lesotho",
      "to": "Liberia",
      "startLat": "-29.609988",
      "startLng": "28.233608",
      "endLat": "6.428055",
      "endLng": "-9.429499",
      "arcAlt": 0.05
    },
    {
      "type": "pull",
      "order": 19,
      "from": "Liberia",
      "to": "Libya",
      "startLat": "6.428055",
      "startLng": "-9.429499",
      "endLat": "26.3351",
      "endLng": "17.2283",
      "arcAlt": 0.05
    },
    {
      "type": "pull",
      "order": 19,
      "from": "Libya",
      "to": "Liechtenstein",
      "startLat": "26.3351",
      "startLng": "17.2283",
      "endLat": "47.166",
      "endLng": "9.5554",
      "arcAlt": 0.05
    },
    {
      "type": "pull",
      "order": 20,
      "from": "Liechtenstein",
      "to": "Lithuania",
      "startLat": "47.166",
      "startLng": "9.5554",
      "endLat": "55.1694",
      "endLng": "23.8813",
      "arcAlt": 0.05
    },
    {
      "type": "pull",
      "order": 20,
      "from": "Luxembourg",
      "to": "Madagascar",
      "startLat": "49.8153",
      "startLng": "6.1296",
      "endLat": "-18.7669",
      "endLng": "46.8691",
      "arcAlt": 0.05
    },
    {
      "type": "pull",
      "order": 20,
      "from": "Madagascar",
      "to": "Malawi",
      "startLat": "-18.7669",
      "startLng": "46.8691",
      "endLat": "-13.2543",
      "endLng": "34.3015",
      "arcAlt": 0.05
    },
    {
      "type": "pull",
      "order": 20,
      "from": "Malawi",
      "to": "Malaysia",
      "startLat": "-13.2543",
      "startLng": "34.3015",
      "endLat": "4.2105",
      "endLng": "101.9758",
      "arcAlt": 0.05
    }
  ]
}
